pycmark_gfm/__init__.py
pycmark_gfm/addnodes.py
pycmark_gfm/transforms.py
pycmark_gfm/blockparser/__init__.py
pycmark_gfm/blockparser/html_processors.py
pycmark_gfm/blockparser/table_processors.py
pycmark_gfm/inlineparser/__init__.py
pycmark_gfm/inlineparser/std_processors.py
pycmark_gfm-0.9.6.dist-info/LICENSE
pycmark_gfm-0.9.6.dist-info/METADATA
pycmark_gfm-0.9.6.dist-info/WHEEL
pycmark_gfm-0.9.6.dist-info/top_level.txt
pycmark_gfm-0.9.6.dist-info/RECORD
