Metadata-Version: 2.1
Name: pycmark-gfm
Version: 0.9.6
Summary: A GitHub Flavored Markdown parser for docutils
Home-page: https://github.com/tk0miya/pycmark-gfm
Author: Takeshi KOMIYA
Author-email: i.tkomiya@gmail.com
License: Apache License 2.0
Download-URL: https://pypi.org/project/pycmark-gfm
Platform: any
Classifier: Development Status :: 3 - Alpha
Classifier: Environment :: Console
Classifier: Environment :: Web Environment
Classifier: Intended Audience :: Developers
Classifier: Intended Audience :: Education
Classifier: License :: OSI Approved :: Apache Software License
Classifier: Operating System :: OS Independent
Classifier: Programming Language :: Python
Classifier: Programming Language :: Python :: 3
Classifier: Programming Language :: Python :: 3.7
Classifier: Programming Language :: Python :: 3.8
Classifier: Programming Language :: Python :: 3.9
Classifier: Programming Language :: Python :: 3.10
Classifier: Topic :: Documentation
Requires-Python: >=3.7
License-File: LICENSE
Requires-Dist: pycmark (>=0.9.6)
Provides-Extra: test
Requires-Dist: tox ; extra == 'test'
Requires-Dist: flake8 ; extra == 'test'
Requires-Dist: flake8-import-order ; extra == 'test'
Requires-Dist: pytest ; extra == 'test'
Requires-Dist: mypy ; extra == 'test'
Requires-Dist: html5lib ; extra == 'test'
